slicertools/__init__.py
slicertools/enums.py
slicertools/materials.py
slicertools/path.py
slicertools/results.py
slicertools/slicers.py
slicertools/utils.py
slicertools/engines/__init__.py
slicertools/engines/base.py
slicertools/engines/__pycache__/__init__.cpython-311.pyc
slicertools/engines/cura/__init__.py
slicertools/engines/cura/__pycache__/__init__.cpython-311.pyc
slicertools/engines/cura/linux/CuraEngine
slicertools/engines/cura/windows/Arcus.dll
slicertools/engines/cura/windows/CuraEngine.exe
slicertools/engines/cura/windows/polyclipping.dll
slicertools/printers/__init__.py
slicertools/printers/creality_base.def.json
slicertools/printers/creality_ender3s1pro.def.json
slicertools/printers/custom.def.json
slicertools/printers/fdmextruder.def.json
slicertools/printers/fdmprinter.def.json
slicertools/printers/__pycache__/__init__.cpython-311.pyc
slicertools-0.1.2.dist-info/LICENSE
slicertools-0.1.2.dist-info/METADATA
slicertools-0.1.2.dist-info/WHEEL
slicertools-0.1.2.dist-info/top_level.txt
slicertools-0.1.2.dist-info/RECORD
