Metadata-Version: 2.1
Name: slicertools
Version: 0.1.2
Summary: A library for slicing 3D models for 3D printing.
Home-page: https://github.com/pysashapy/slicertools
Author: Alexander Ibragimov
Author-email: sasha.2000ibr@example.com
Classifier: Programming Language :: Python :: 3
Classifier: License :: OSI Approved :: GNU General Public License v3 (GPLv3)
Classifier: Operating System :: Microsoft :: Windows
Classifier: Operating System :: POSIX :: Linux
Requires-Python: >=3.9
License-File: LICENSE
Requires-Dist: trimesh[easy]
